MANIFEST.in
README.rst
setup.py
django_notices/__init__.py
django_notices/constants.py
django_notices/context_processors.py
django_notices/helpers.py
django_notices/middleware.py
django_notices.egg-info/PKG-INFO
django_notices.egg-info/SOURCES.txt
django_notices.egg-info/dependency_links.txt
django_notices.egg-info/requires.txt
django_notices.egg-info/top_level.txt