Metadata-Version: 1.0
Name: django-notices
Version: 0.2
Summary: A message notification system for Django.
Home-page: http://github.com/dcramer/django-notices
Author: David Cramer
Author-email: dcramer@gmail.com
License: UNKNOWN
Platform: UNKNOWN
